dt_range/__init__.py
tests/__init__.py
tests/test_daterange.py
tests/test_hourrange.py
dt_range-1.0.dist-info/LICENSE
dt_range-1.0.dist-info/METADATA
dt_range-1.0.dist-info/WHEEL
dt_range-1.0.dist-info/top_level.txt
dt_range-1.0.dist-info/RECORD
