Metadata-Version: 2.1
Name: dt-range
Version: 1.0
Summary: Generators for datetime.
Home-page: https://github.com/nanato12/dt-range
Author: nanato12
Author-email: admin@nanato12.info
License: Apache License 2.0
Keywords: dt-range datetime-range datetime-generator
Platform: UNKNOWN
Classifier: License :: OSI Approved :: Apache Software License
Classifier: Programming Language :: Python :: 3
Classifier: Programming Language :: Python :: 3 :: Only
Classifier: Programming Language :: Python :: 3.6
Classifier: Programming Language :: Python :: 3.7
Classifier: Programming Language :: Python :: 3.8
Classifier: Programming Language :: Python :: 3.9
Requires-Python: >=3.6
License-File: LICENSE
